CHANGES.txt
LICENSE
MANIFEST.in
README.rst
setup.py
aiogibson/__init__.py
aiogibson/commands.py
aiogibson/connection.py
aiogibson/consts.py
aiogibson/errors.py
aiogibson/parser.py
aiogibson/pool.py
aiogibson.egg-info/PKG-INFO
aiogibson.egg-info/SOURCES.txt
aiogibson.egg-info/dependency_links.txt
aiogibson.egg-info/top_level.txt