Metadata-Version: 1.1
Name: aiogibson
Version: 0.1.3
Summary: asyncio (PEP 3156) Gibson cache support
Home-page: https://github.com/jettify/aiogibson
Author: Nikolay Novik
Author-email: nickolainovik@gmail.com
License: MIT
Platform: POSIX
Classifier: License :: OSI Approved :: MIT License
Classifier: Development Status :: 4 - Beta
Classifier: Programming Language :: Python
Classifier: Programming Language :: Python :: 3
Classifier: Programming Language :: Python :: 3.3
Classifier: Programming Language :: Python :: 3.4
Classifier: Operating System :: POSIX
Classifier: Environment :: Web Environment
Classifier: Intended Audience :: Developers
Classifier: Topic :: Software Development
Classifier: Topic :: Software Development :: Libraries
